[
  {
    "name": "Банановий кекс",
    "category": "Сніданки",
    "subcategory": "Солодкі сніданки",
    "description": "КБЖВ оригінального рецепта (без замін) на 1 порцію",
    "nutritionalValue": [786, 17, 52, 67],
    "ingredients": [
      {
        "name": "Яйце",
        "amount": "1 шт",
        "alternative": "2 ст.л. вівсяних пластівців + 2 ст.л. води"
      },
      {
        "name": "Банан",
        "amount": "1 шт",
        "alternative": "Ягоди, персик, диня"
      },
      {
        "name": "Вершкове масло",
        "amount": "50 г",
        "alternative": "Рослинна олія"
      },
      {
        "name": "Горіхи волоські",
        "amount": "15 г",
        "alternative": "Інші горіхи, насіння"
      },
      {
        "name": "Цільнозернове борошно",
        "amount": "15 г",
        "alternative": "Інше борошно"
      },
      {
        "name": "Розпушувач",
        "amount": "На кінчик ножа",
        "alternative": "Сода"
      }
    ],
    "steps": [
      "Банан розім'яти виделкою до консистенції пюре і додати до нього яйце.",
      "Розтопити вершкове масло, дати охолонути 2 хвилини та додати до банана.",
      "Горіхи подрібнити та додати до банана.",
      "Додати борошно та розпушувач і перемішати до однорідності.",
      "Отриману суміш перекласти у форму для випікання (можна змастити форму олією або застелити пергаментом).",
      "Відправляємо в духовку на 30 хвилин на 180 градусів."
    ]
  },

  {
    "name": "Кокосовий магкейк",
    "category": "Сніданки",
    "subcategory": "Солодкі сніданки",
    "description": "КБЖВ оригінального рецепта (без замін) на 1 порцію",
    "nutritionalValue": [476, 20, 20, 53],
    "ingredients": [
      {
        "name": "Яйце",
        "amount": "1 шт",
        "alternative": "2 ст.л. вівсяних пластівців + 2 ст.л. води"
      },
      {
        "name": "М'який сир 5%",
        "amount": "100 г",
        "alternative": "Сир кисломолочний"
      },
      {
        "name": "Кокосова стружка",
        "amount": "1 ст.л.",
        "alternative": "Какао"
      },
      {
        "name": "Рисове борошно",
        "amount": "60 г",
        "alternative": "Інше борошно"
      },
      {
        "name": "Замінник цукру",
        "amount": "На смак",
        "alternative": "Цукор, мед (порахувати КБЖВ), інший замінник цукру"
      },
      {
        "name": "Розпушувач",
        "amount": "На кінчик ножа",
        "alternative": "Сода"
      }
    ],
    "steps": [
      "Всі інгедієнти змішати.",
      "Поставити у мікрохвильовку на 3 хвилини."
    ]
  },

  {
    "name": "Яблучні оладки",
    "category": "Сніданки",
    "subcategory": "Солодкі сніданки",
    "description": "КБЖВ оригінального рецепта (без замін) на 1 порцію",
    "nutritionalValue": [312, 9, 5, 59],
    "ingredients": [
      {
        "name": "Яйце",
        "amount": "1 шт",
        "alternative": "2 ст.л. вівсяних пластівців + 2 ст.л. води"
      },
      {
        "name": "Яблуко",
        "amount": "1 шт",
        "alternative": "Персик, банан"
      },
      {
        "name": "Рисове борошно",
        "amount": "50 г",
        "alternative": "Інше борошно"
      },
      {
        "name": "Замінник цукру",
        "amount": "На смак",
        "alternative": "Цукор, мед (звернись до куратора порахувати КБЖВ)"
      },
      {
        "name": "Розпушувач",
        "amount": "На кінчик ножа",
        "alternative": "Сода"
      }
    ],
    "steps": [
      "Яблуко очистити від шкіри та натерти.",
      "Додати борошно, яйце, підсолоджувач і розпушувач.",
      "Все перемішати. Тісто не має розтікатися. Повинно вийти так, щоб можна було зліпити кульки або будь-яку іншу форму. Якщо не виходить, додати ще трохи борошна.",
      "Сформувати з маси будь-яку зручну форму.Можна зробити круглі або надати форму оладок.",
      "Смажити на а/п сковороді без олії або з невеликою кількістю олії."
    ]
  },

  {
    "name": "Панкейки",
    "category": "Сніданки",
    "subcategory": "Солодкі сніданки",
    "description": "КБЖВ оригінального рецепта (без замін) на 1 порцію",
    "nutritionalValue": [298, 10, 4, 54],
    "ingredients": [
      {
        "name": "Яйце маленьке",
        "amount": "1 шт",
        "alternative": "2 ст.л. вівсяних пластівців + 2 ст.л. води"
      },
      {
        "name": "Знежирине молоко",
        "amount": "50 мл",
        "alternative": "Інше молоко, вершки, рослинне молоко, кефір"
      },
      {
        "name": "Рисове борошно",
        "amount": "60 г",
        "alternative": "Інше борошно"
      },
      {
        "name": "Замінник цукру",
        "amount": "На смак",
        "alternative": "Цукор, мед (звернись до куратора порахувати КБЖВ)"
      },
      {
        "name": "Розпушувач",
        "amount": "На кінчик ножа",
        "alternative": "Сода"
      },
      {
        "name": "Ванілін",
        "amount": "5 г",
        "alternative": "Не додавати"
      }
    ],
    "steps": [
      "Молоко змішати з яйцем, збити.",
      "Додати сухи інгредієнти, перемішати.",
      "Смажити на а/п сковородці без олії по 1-1,5 хвилини з кожного боку."
    ]
  },

  {
    "name": "Млинці з медом",
    "category": "Сніданки",
    "subcategory": "Солодкі сніданки",
    "description": "КБЖВ оригінального рецепта (без замін) на 1 порцію",
    "nutritionalValue": [489, 13, 30, 45],
    "ingredients": [
      {
        "name": "Яйце",
        "amount": "1 шт",
        "alternative": "2 ст.л. вівсяних пластівців + 2 ст.л. води"
      },
      {
        "name": "Молоко 2.2%",
        "amount": "40 мл",
        "alternative": "Вершки, рослинне молоко, кефір"
      },
      {
        "name": "Рисове борошно",
        "amount": "20 г",
        "alternative": "Інше борошно"
      },
      {
        "name": "Мед",
        "amount": "10 г",
        "alternative": "Цукор, кленовий сироп"
      },
      {
        "name": "Вода",
        "amount": "65 г",
        "alternative": "Немає альтернативи"
      },
      {
        "name": "Рослинна олія",
        "amount": "1 ч.л.",
        "alternative": "Вершкове масло"
      },
      {
        "name": "Сіль",
        "amount": "Дрібка",
        "alternative": "Немає альтернативи"
      },
      {
        "name": "Сода",
        "amount": "1/4 ч.л.",
        "alternative": "Немає альтернативи"
      },
      {
        "name": "Мед для начинки",
        "amount": "30 г або 3 ч.л.",
        "alternative": "Варення"
      },
      {
        "name": "Волоський горіх",
        "amount": "30 г",
        "alternative": "Інші горіхи"
      }
    ],
    "steps": [
      "Яйце збити із сіллю та медом.",
      "Додати молоко, олію, воду кімнатної температури, соду.",
      "Просіяти борошно.",
      "Вилити на розпечену сковорідку по 3 ст. л. суміші. Обсмажувати з двох сторін по 1-2 хвилини.",
      "Для начинки подрібнити горіхи та перемішати з медом.",
      "Додати начинку на кожен млинець та згорнути трикутником."
    ]
  },

  {
    "name": "Шоколадне суфле",
    "category": "Сніданки",
    "subcategory": "Солодкі сніданки",
    "description": "КБЖВ оригінального рецепта (без замін) на 1 порцію",
    "nutritionalValue": [276, 18, 7, 37],
    "ingredients": [
      {
        "name": "Ряжанка",
        "amount": "150 мл",
        "alternative": "Йогурт"
      },
      {
        "name": "Какао",
        "amount": "1 ст.л.",
        "alternative": "Кероб"
      },
      {
        "name": "Замінник цукру",
        "amount": "На смак",
        "alternative": "Цукор, мед (звернись до куратора порахувати КБЖВ)"
      },
      {
        "name": "Желатин",
        "amount": "15 г",
        "alternative": "Агар-агар"
      },
      {
        "name": "Ванілін",
        "amount": "На кінчик ножа",
        "alternative": "Не додавати"
      },
      {
        "name": "Мед",
        "amount": "1 ст.л.",
        "alternative": "Цукор, кленовий сироп, замінник цукру"
      }
    ],
    "steps": [
      "Желатин розчинити на водяній бані або вмікрохвильовці.",
      "Змішати всі сухі інгредієнти з желатином і ряжанкою.",
      "Збити все блендером",
      "Прибрати в холодильник на годину або на ніч."
    ]
  }
]